atuin/__init__.py
atuin/__main__.py
atuin/challenges/__init__.py
atuin/challenges/parser.py
atuin/commands/__init__.py
atuin/commands/base.py
atuin/core/__init__.py
atuin/core/colorlogging.py
atuin/core/initialize.py
atuin/core/management.py
atuin/defaults/__init__.py
atuin/defaults/config.ini
atuin/defaults/templates/blank.md.template
atuin/defaults/templates/challenge.html.template
atuin/defaults/templates/challenge.md.template
atuin/defaults/templates/default.template
atuin/defaults/templates/random.py.template
atuin-0.0.4.dist-info/METADATA
atuin-0.0.4.dist-info/RECORD
atuin-0.0.4.dist-info/WHEEL
atuin-0.0.4.dist-info/entry_points.txt
atuin-0.0.4.dist-info/top_level.txt
